bleak_winrt/__init__.py
bleak_winrt/_winrt.pyd
bleak_winrt/_winrt.pyi
bleak_winrt/py.typed
bleak_winrt/windows/devices/bluetooth/__init__.py
bleak_winrt/windows/devices/bluetooth/__init__.pyi
bleak_winrt/windows/devices/bluetooth/advertisement/__init__.py
bleak_winrt/windows/devices/bluetooth/advertisement/__init__.pyi
bleak_winrt/windows/devices/bluetooth/background/__init__.py
bleak_winrt/windows/devices/bluetooth/background/__init__.pyi
bleak_winrt/windows/devices/bluetooth/genericattributeprofile/__init__.py
bleak_winrt/windows/devices/bluetooth/genericattributeprofile/__init__.pyi
bleak_winrt/windows/devices/enumeration/__init__.py
bleak_winrt/windows/devices/enumeration/__init__.pyi
bleak_winrt/windows/foundation/__init__.py
bleak_winrt/windows/foundation/__init__.pyi
bleak_winrt/windows/foundation/collections/__init__.py
bleak_winrt/windows/foundation/collections/__init__.pyi
bleak_winrt/windows/storage/streams/__init__.py
bleak_winrt/windows/storage/streams/__init__.pyi
bleak_winrt-1.2.0.dist-info/LICENSE
bleak_winrt-1.2.0.dist-info/METADATA
bleak_winrt-1.2.0.dist-info/WHEEL
bleak_winrt-1.2.0.dist-info/top_level.txt
bleak_winrt-1.2.0.dist-info/RECORD
